{
  "backup_date": "2025-12-04T20:35:53.291Z",
  "migration_date": "2025-12-04",
  "tables": [
    "candidates",
    "candidate_profiles",
    "candidate_resumes",
    "job_applications",
    "job_matches",
    "candidate_disc_assessments",
    "candidate_typing_assessments",
    "candidate_ai_analysis",
    "jobs",
    "companies",
    "agencies",
    "bpoc_users",
    "bpoc_profiles"
  ],
  "record_counts": {
    "candidates": 46,
    "candidate_profiles": 46,
    "candidate_resumes": 81,
    "job_applications": 6,
    "job_matches": 104,
    "candidate_disc_assessments": 54,
    "candidate_typing_assessments": 66,
    "candidate_ai_analysis": 87,
    "jobs": 22,
    "companies": 31,
    "agencies": 1,
    "bpoc_users": 6,
    "bpoc_profiles": 0
  }
}